[{"username":"","organizationName":"green org","organizationType":"Company","type":"Solution Provider","logo":"..\/users\/assets\/comLogo.png","aboutMedia":"..\/users\/assets\/comLogo.png","shortAbout":"some short about","founded":"2010","employees":"20-30","hq":"USA","story":"some story","specializations":["Green energy","Offshore wind"],"organizationWebsite":"https:\/\/www.aiub.edu\/","organizationAddress":"New York, USA","mapsLink":"https:\/\/www.google.com\/maps\/place\/American+International+University+-+Bangladesh+(AIUB)\/@23.8228583,90.4295391,15.44z\/data=!4m6!3m5!1s0x3755c711d13bbec7:0xc47f7c3e8e2263f2!8m2!3d23.8221242!4d90.4274063!16s%2Fm%2F026zp7q?entry=ttu","contactName":"John Smith","contactEmail":"tyamshitr@gmail.com"},{"username":"solPro","organizationName":null,"organizationType":"","type":"solutionProvider","logo":"..\/users\/assets\/1689653676comLogo.png","aboutMedia":"","shortAbout":"","founded":"","employees":"","hq":"","story":"","specializations":"","organizationWebsite":"","organizationAddress":"","mapsLink":"","contactName":"","contactEmail":""}]